neurotron/__init__.py
neurotron/ansi.py
neurotron/cluster/__init__.py
neurotron/cluster/cells.py
neurotron/cluster/monitor.py
neurotron/cluster/setup.py
neurotron/cluster/terminal.py
neurotron/cluster/token.py
neurotron/cluster/toy.py
neurotron/cluster/trainer.py
neurotron/math/__init__.py
neurotron/math/__old_init__.py
neurotron/math/attribute.py
neurotron/math/field.py
neurotron/math/helper.py
neurotron/math/matfun.py
neurotron/math/matrix.py
neurotron/neurotron.py
neurotron/screen.py
neurotron/shakespear.py
neurotron/util.py
neurotron-0.1.3.dist-info/METADATA
neurotron-0.1.3.dist-info/WHEEL
neurotron-0.1.3.dist-info/RECORD
