Metadata-Version: 2.1
Name: neurotron
Version: 0.1.3
Summary: 
Author: iHux
Author-email: hugo.pristauz@gmail.com
Requires-Python: >=3.11,<4.0
Classifier: Programming Language :: Python :: 3
Classifier: Programming Language :: Python :: 3.11
Classifier: Programming Language :: Python :: 3.12
Requires-Dist: matplotlib (==3.8.2)
Requires-Dist: numpy (>=1.26.2,<2.0.0)
Requires-Dist: pendulum (>=2.1.2,<3.0.0)
Requires-Dist: ypstruct (>=0.0.2,<0.0.3)
